examples/__init__.py
tuning-2020.8.28.15.39.17.dist-info/METADATA
tuning-2020.8.28.15.39.17.dist-info/RECORD
tuning-2020.8.28.15.39.17.dist-info/WHEEL
tuning-2020.8.28.15.39.17.dist-info/entry_points.txt
tuning-2020.8.28.15.39.17.dist-info/top_level.txt
